{
  "CoverWidth": 192.0,
  "CoverHeight": 120.0,
  "IsSelected": false,
  "IsLastHit": false,
  "Aid": "41446451",
  "SeasonId": null,
  "EpisodeId": null,
  "Title": "Go语言入门到精通（一）",
  "Uploader": "Python宇宙无敌",
  "Mid": "259245663",
  "Description": "Go（又称Golang）是Google开发的一种静态强类型、编译型、并发型，并具有垃圾回收功能的编程语言。",
  "CoverURL": "http://i2.hdslb.com/bfs/archive/a9847331b38b136838a5fd7301624a8882125b50.jpg",
  "CoverImageSource": null,
  "Tag": null,
  "DownloadTimeRelative": 144449527,
  "DownloadTime": null,
  "CreateDate": "2019-01-23 12:51",
  "TotalTime": "00:00:00",
  "Parts": null,
  "FontSize6": 10.0,
  "FontSize8": 12.0,
  "FontSize10": 14.0,
  "FontSize12": 16.0,
  "FontSize14": 18.0,
  "FontSize16": 20.0,
  "FontSize18": 22.0,
  "FontSize20": 24.0,
  "FontSize22": 26.0,
  "FontSize24": 28.0,
  "FontSize30": 34.0,
  "FontSize34": 38.0
}